MANIFEST.in
README.txt
setup.py
docs/HISTORY.txt
silva/__init__.py
silva.pageactions.mailpdf.egg-info/PKG-INFO
silva.pageactions.mailpdf.egg-info/SOURCES.txt
silva.pageactions.mailpdf.egg-info/dependency_links.txt
silva.pageactions.mailpdf.egg-info/namespace_packages.txt
silva.pageactions.mailpdf.egg-info/not-zip-safe
silva.pageactions.mailpdf.egg-info/requires.txt
silva.pageactions.mailpdf.egg-info/top_level.txt
silva/pageactions/__init__.py
silva/pageactions/mailpdf/__init__.py
silva/pageactions/mailpdf/configure.zcml
silva/pageactions/mailpdf/mailpdf.py
silva/pageactions/mailpdf/i18n/pageactions.pot
silva/pageactions/mailpdf/i18n/de/LC_MESSAGES/pageactions.mo
silva/pageactions/mailpdf/i18n/de/LC_MESSAGES/pageactions.po
silva/pageactions/mailpdf/i18n/en/LC_MESSAGES/pageactions.mo
silva/pageactions/mailpdf/i18n/en/LC_MESSAGES/pageactions.po
silva/pageactions/mailpdf/mailpdf_templates/mailpdfaction.cpt
silva/pageactions/mailpdf/schema/mail-pageactions.xml