Metadata-Version: 1.1
Name: silva.pageactions.mailpdf
Version: 1.0.2
Summary: Send the current by mail as a PDF.
Home-page: UNKNOWN
Author: Infrae
Author-email: info@infrae.com
License: BSD
Keywords: silva pageactions mail pdf
Platform: UNKNOWN
Classifier: Framework :: Zope2
Classifier: Programming Language :: Python
Classifier: Topic :: Software Development :: Libraries :: Python Modules
